prioritree/__init__.py
prioritree/forms.py
prioritree/main.py
prioritree_xaudier-0.0.1.dist-info/LICENSE
prioritree_xaudier-0.0.1.dist-info/METADATA
prioritree_xaudier-0.0.1.dist-info/WHEEL
prioritree_xaudier-0.0.1.dist-info/top_level.txt
prioritree_xaudier-0.0.1.dist-info/RECORD
